pyfabrik/__init__.py
pyfabrik-0.4.0.dist-info/LICENSE
pyfabrik-0.4.0.dist-info/WHEEL
pyfabrik-0.4.0.dist-info/METADATA
pyfabrik-0.4.0.dist-info/RECORD
