Metadata-Version: 2.1
Name: pyfabrik
Version: 0.4.0
Summary: Python 3 implementation of FABRIK (Forward And Backward Reaching Inverse Kinematics) algorithm.
Home-page: https://github.com/saleone/pyfabrik
License: GPL-3.0-or-later
Author: Saša Savić
Author-email: sasa@savic.one
Requires-Python: >=3.6,<4.0
Classifier: License :: OSI Approved :: GNU General Public License v3 (GPLv3)
Classifier: License :: OSI Approved :: GNU General Public License v3 or later (GPLv3+)
Classifier: Operating System :: OS Independent
Classifier: Programming Language :: Python :: 3
Classifier: Programming Language :: Python :: 3 :: Only
Classifier: Programming Language :: Python :: 3.6
Classifier: Programming Language :: Python :: 3.7
Classifier: Programming Language :: Python :: 3.8
Classifier: Programming Language :: Python :: 3.9
Requires-Dist: vectormath (>=0.2.2,<0.3.0)
Project-URL: Repository, https://github.com/saleone/pyfabrik
